{"notes_architecture_index.md":"D1OJfmVz","notes_cluster_deploy_index.md":"DFLGh-FH","notes_faq_index.md":"CCcKl9mU","notes_version_describe_index.md":"96xH6mVU","index.md":"DK_TNZN3","notes_deploy_example_linux_systemd_deploy_index.md":"BEjDftfN","notes_change_index.md":"Dt7vo6Kb","notes_intro_index.md":"ZttZjrC0","notes_deploy_example_docker_cluster_deploy_index.md":"DBwKL-E7","notes_deploy_example_linux_deploy_index.md":"BnNEaeCp","notes_quick_started_index.md":"Cfxk36ro","notes_performance_index.md":"Dfda0rH1","notes_env_config_index.md":"Bgsd9hIf","notes_deploy_example_nacos_to_rnacos_doc_index.md":"BmPAvUjM"}
