{"index.md":"DllKZxJ8","notes_architecture_index.md":"C7TJRW_J","notes_change_index.md":"CjNwBlp5","notes_cluster_deploy_index.md":"CNxuRL8y","notes_deploy_example_docker_cluster_deploy_index.md":"CUPbuuGF","notes_deploy_example_linux_deploy_index.md":"An8cyqo2","notes_deploy_example_linux_systemd_deploy_index.md":"Dysur9an","notes_deploy_example_nacos_to_rnacos_doc_index.md":"Qqu7c7yk","notes_env_config_index.md":"BsQBJY2H","notes_faq_index.md":"CR4bergw","notes_intro_index.md":"yid90OhD","notes_performance_index.md":"C7_PCSbT","notes_quick_started_index.md":"DVECtBYV","notes_version_describe_index.md":"D6h_hYmS"}
